qrplatba/__init__.py
qrplatba/spayd.py
qrplatba/svg.py
qrplatba-1.1.1.dist-info/LICENSE
qrplatba-1.1.1.dist-info/METADATA
qrplatba-1.1.1.dist-info/WHEEL
qrplatba-1.1.1.dist-info/RECORD
