Metadata-Version: 2.1
Name: qrplatba
Version: 1.1.1
Summary: QR platba SVG QR code and SPAYD string generator.
Home-page: https://github.com/ViktorStiskala/python-qrplatba
License: MIT
Author: Viktor Stískala
Author-email: viktor@stiskala.cz
Requires-Python: >=3.8,<4.0
Classifier: Intended Audience :: Developers
Classifier: License :: OSI Approved :: MIT License
Classifier: Operating System :: OS Independent
Classifier: Programming Language :: Python
Classifier: Programming Language :: Python :: 3
Classifier: Programming Language :: Python :: 3.8
Classifier: Programming Language :: Python :: 3.9
Classifier: Programming Language :: Python :: 3.10
Classifier: Programming Language :: Python :: 3.11
Classifier: Programming Language :: Python :: 3.10
Classifier: Programming Language :: Python :: 3.11
Classifier: Programming Language :: Python :: 3.8
Classifier: Programming Language :: Python :: 3.9
Classifier: Topic :: Software Development :: Libraries
Classifier: Topic :: Software Development :: Libraries :: Python Modules
Requires-Dist: qrcode (>=7.4,<8.0)
Project-URL: Repository, https://github.com/ViktorStiskala/python-qrplatba
